{
  "STUDENT": [
    {
      "id": 0,
      "name": "Doe",
      "prenom": "John",
      "group": "3BIM",
      "entretien": "Non"
    },
    {
      "id": 1,
      "name": "Doe",
      "prenom": "Marie",
      "group": "3BB",
      "entretien": "Oui"
    },
    {
      "id": 2,
      "name": "dd",
      "prenom": "ss",
      "group": "3BIM",
      "entretien": "Oui"
    },
    {
      "id": 3,
      "name": "ss",
      "prenom": "ss",
      "group": "4BB",
      "entretien": "Non"
    },
    {
      "id": 4,
      "name": "s",
      "prenom": "x",
      "group": "3BB",
      "entretien": "Non"
    }
  ],
  "COMPANY": [
    {
      "id": 0,
      "name": "x",
      "secteur": "x",
      "effectif": "inf250",
      "entretien": "Non",
      "forum": "Oui",
      "responsable": "x",
      "mail": "x"
    }
  ]
}